{
  "report_date": "2026-03-12",
  "market_base_level": [
    {
      "metric": "DR001收盘价",
      "value": 1.36,
      "percentile": 30.1,
      "unit": ""
    },
    {
      "metric": "中债10年期收益率",
      "value": 1.8075,
      "percentile": 24.7,
      "unit": "%"
    },
    {
      "metric": "美债10年期收益率",
      "value": 4.21,
      "percentile": 50.3,
      "unit": "%"
    },
    {
      "metric": "人民币汇率",
      "value": 6.8959,
      "percentile": 3.5,
      "unit": "%"
    },
    {
      "metric": "融资买入占比",
      "value": 9.7144,
      "percentile": 71.5,
      "unit": "%"
    },
    {
      "metric": "散户小单净流入",
      "value": 500133.6521,
      "percentile": null,
      "unit": ""
    }
  ],
  "weekly_anomalies": [
    {
      "date": "2026-03-13",
      "metric": "VIX波动率",
      "type": "单日波动",
      "description": "VIX波动率周度下行 17.84%，当前值 24.2300。",
      "pct_change": -0.1784,
      "chart_path": "C:\\Users\\xiayi\\OneDrive\\Desktop\\Market_AI_Project\\charts\\VIX波动率_2026-03-13.png"
    },
    {
      "date": "2026-03-13",
      "metric": "石油价格",
      "type": "极值偏离",
      "description": "石油价格呈现上行偏离，当前值 91.7400，偏离一年均值 3.7σ。",
      "z_score": 3.67,
      "chart_path": "C:\\Users\\xiayi\\OneDrive\\Desktop\\Market_AI_Project\\charts\\石油价格_2026-03-13.png"
    },
    {
      "date": "2026-03-13",
      "metric": "人民币汇率",
      "type": "极值偏离",
      "description": "人民币汇率呈现下探偏离，当前值 6.8959，偏离一年均值 2.5σ。",
      "z_score": -2.47,
      "chart_path": "C:\\Users\\xiayi\\OneDrive\\Desktop\\Market_AI_Project\\charts\\人民币汇率_2026-03-13.png"
    },
    {
      "date": "2026-03-13",
      "metric": "融资买入占比",
      "type": "单日波动",
      "description": "融资买入占比周度上行 5.81%，当前值 9.7144。",
      "pct_change": 0.0581,
      "chart_path": "C:\\Users\\xiayi\\OneDrive\\Desktop\\Market_AI_Project\\charts\\融资买入占比_2026-03-13.png"
    },
    {
      "date": "2026-03-13",
      "metric": "散户小单净流入",
      "type": "单日波动",
      "description": "散户小单净流入周度下行 48.70%，当前值 500133.6521。",
      "pct_change": -0.487,
      "chart_path": "C:\\Users\\xiayi\\OneDrive\\Desktop\\Market_AI_Project\\charts\\散户小单净流入_2026-03-13.png"
    }
  ],
  "baseline_chart_paths": [
    "C:\\Users\\xiayi\\OneDrive\\Desktop\\Market_AI_Project\\charts\\baseline_1_2026-03-12.png",
    "C:\\Users\\xiayi\\OneDrive\\Desktop\\Market_AI_Project\\charts\\baseline_2_2026-03-12.png",
    "C:\\Users\\xiayi\\OneDrive\\Desktop\\Market_AI_Project\\charts\\baseline_3_2026-03-12.png"
  ]
}